pynamematcher/__init__.py
pynamematcher/matcher.py
pynamematcher/version.py
pynamematcher/data/names.csv
PyNameMatcher-0.1.2.dist-info/LICENSE
PyNameMatcher-0.1.2.dist-info/METADATA
PyNameMatcher-0.1.2.dist-info/WHEEL
PyNameMatcher-0.1.2.dist-info/top_level.txt
PyNameMatcher-0.1.2.dist-info/RECORD
