Metadata-Version: 2.1
Name: PyNameMatcher
Version: 0.1.2
Summary: Simple library for matching first names with possible variations
Home-page: https://github.com/constituentvoice/PyNameMatcher
Author: Constituent Voice LLC
Author-email: chris.brown@constituentvoice.com
License: Apache
Platform: UNKNOWN
Requires-Dist: Metaphone
